concurrentbuffer/__init__.py
concurrentbuffer/_version.py
concurrentbuffer/commander.py
concurrentbuffer/factory.py
concurrentbuffer/info.py
concurrentbuffer/iterator.py
concurrentbuffer/manager.py
concurrentbuffer/memory.py
concurrentbuffer/process.py
concurrentbuffer/producer.py
concurrentbuffer/state.py
concurrentbuffer/system.py
concurrentbuffer-0.0.8.dist-info/LICENSE
concurrentbuffer-0.0.8.dist-info/METADATA
concurrentbuffer-0.0.8.dist-info/WHEEL
concurrentbuffer-0.0.8.dist-info/top_level.txt
concurrentbuffer-0.0.8.dist-info/RECORD
