Metadata-Version: 2.1
Name: concurrentbuffer
Version: 0.0.8
Author-email: Mart van Rijthoven <mart.vanrijthoven@gmail.com>
License: MIT License
Project-URL: Homepage, https://github.com/martvanrijthoven/concurrentbuffer/
Classifier: Programming Language :: Python :: 3
Classifier: Programming Language :: Python :: 3.8
Classifier: Programming Language :: Python :: 3.9
Classifier: Programming Language :: Python :: 3.10
Classifier: Programming Language :: Python :: 3.11
Classifier: Programming Language :: Python :: 3 :: Only
Classifier: License :: OSI Approved :: MIT License
Classifier: Operating System :: OS Independent
Classifier: Development Status :: 4 - Beta
Requires-Python: >=3.8
License-File: LICENSE
Requires-Dist: numpy (>=1.18.1)
